geekbot_mcp/__init__.py
geekbot_mcp/gb_api.py
geekbot_mcp/models.py
geekbot_mcp/server.py
geekbot_mcp/settings.py
geekbot_mcp/prompts/__init__.py
geekbot_mcp/prompts/weekly_rollup_report.py
geekbot_mcp/tools/__init__.py
geekbot_mcp/tools/fetch_poll_results.py
geekbot_mcp/tools/fetch_reports.py
geekbot_mcp/tools/list_members.py
geekbot_mcp/tools/list_polls.py
geekbot_mcp/tools/list_standups.py
geekbot_mcp/tools/post_report.py
iflow_mcp_geekbot_mcp-0.3.4.dist-info/METADATA
iflow_mcp_geekbot_mcp-0.3.4.dist-info/WHEEL
iflow_mcp_geekbot_mcp-0.3.4.dist-info/entry_points.txt
iflow_mcp_geekbot_mcp-0.3.4.dist-info/licenses/LICENSE
iflow_mcp_geekbot_mcp-0.3.4.dist-info/RECORD
