Metadata-Version: 2.4
Name: iflow-mcp_geekbot-mcp
Version: 0.3.4
Summary: Model Context Protocol (MCP) server integrating Geekbot data and tools to Claude AI
Project-URL: Homepage, https://github.com/geekbot-com/geekbot-mcp
Project-URL: Bug Tracker, https://github.com/geekbot-com/geekbot-mcp/issues
Author-email: Geekbot <support@geekbot.com>
License: MIT
License-File: LICENSE
Keywords: ai,anthropic,api,chatbot,claude,geekbot,integration,llm,mcp
Classifier: License :: OSI Approved :: MIT License
Classifier: Operating System :: OS Independent
Classifier: Programming Language :: Python :: 3
Classifier: Programming Language :: Python :: 3.10
Classifier: Programming Language :: Python :: 3.11
Classifier: Programming Language :: Python :: 3.12
Classifier: Topic :: Communications :: Chat
Classifier: Topic :: Internet
Classifier: Topic :: Scientific/Engineering :: Artificial Intelligence
Classifier: Topic :: Software Development :: Libraries :: Python Modules
Requires-Python: >=3.10
Requires-Dist: aiohttp>=3.11.14
Requires-Dist: jinja2>=3.1.6
Requires-Dist: mcp[cli]>=1.5.0
Requires-Dist: python-dotenv>=1.1.0
